example/__init__.py
example/config.py
example/data/Clinical-01-06-23-1-V2A-fastqs/Sequencing_report-01-06-23-1-V2A-All.csv
example/data/Clinical-01-06-23-1-V2A-fastqs/fastqs/CORVASEQ-CLT-013517_barcode04.fastq
example/data/Clinical-01-06-23-1-V2A-fastqs/fastqs/CORVASEQ-CLT-013522_barcode09.fastq
example/data/Clinical-01-06-23-1-V2A-fastqs/gisaid_uploader.log
example/data/Clinical-01-06-23-1-V2A-fastqs/ncbi/biosample_attributes.tsv
example/data/Clinical-01-06-23-1-V2A-fastqs/ncbi/genbank-metadata.tsv
example/data/Clinical-01-06-23-1-V2A-fastqs/ncbi/genbank.xml
example/data/Clinical-01-06-23-1-V2A-fastqs/ncbi/genbank.zip
example/data/Clinical-01-06-23-1-V2A-fastqs/ncbi/sra-metadata.tsv
example/data/Clinical-01-06-23-1-V2A-fastqs/ncbi/sra_biosample.xml
example/data/Clinical-01-06-23-1-V2A-fastqs/ncbi_test/biosample_attributes.tsv
example/data/Clinical-01-06-23-1-V2A-fastqs/ncbi_test/bs_sra_reports/01-06-23-1-V2A/report.1.xml
example/data/Clinical-01-06-23-1-V2A-fastqs/ncbi_test/bs_sra_reports/01-06-23-1-V2A/report.2.xml
example/data/Clinical-01-06-23-1-V2A-fastqs/ncbi_test/bs_sra_reports/01-06-23-1-V2A/report.3.xml
example/data/Clinical-01-06-23-1-V2A-fastqs/ncbi_test/bs_sra_reports/01-06-23-1-V2A/report.4.xml
example/data/Clinical-01-06-23-1-V2A-fastqs/ncbi_test/bs_sra_reports/01-06-23-1-V2A/report.5.xml
example/data/Clinical-01-06-23-1-V2A-fastqs/ncbi_test/bs_sra_reports/01-06-23-1-V2A/report.6.xml
example/data/Clinical-01-06-23-1-V2A-fastqs/ncbi_test/bs_sra_reports/01-06-23-1-V2A/report.xml
example/data/Clinical-01-06-23-1-V2A-fastqs/ncbi_test/genbank-metadata.tsv
example/data/Clinical-01-06-23-1-V2A-fastqs/ncbi_test/genbank.xml
example/data/Clinical-01-06-23-1-V2A-fastqs/ncbi_test/genbank.zip
example/data/Clinical-01-06-23-1-V2A-fastqs/ncbi_test/samples2exclude.txt
example/data/Clinical-01-06-23-1-V2A-fastqs/ncbi_test/sra-metadata.tsv
example/data/Clinical-01-06-23-1-V2A-fastqs/ncbi_test/sra_biosample.xml
ncbi_submit-0.8.1.dist-info/LICENSE
ncbi_submit-0.8.1.dist-info/METADATA
ncbi_submit-0.8.1.dist-info/WHEEL
ncbi_submit-0.8.1.dist-info/entry_points.txt
ncbi_submit-0.8.1.dist-info/RECORD
