Metadata-Version: 2.1
Name: ncbi-submit
Version: 0.8.1
Summary: A tool for submitting to NCBI (SRA, BioSample, & GenBank).
Home-page: https://github.com/enviro-lab/ncbi-submit
License: MIT
Keywords: ncbi,submission,upload
Author: Sam Kunkleman
Author-email: skunklem@uncc.edu
Maintainer: Sam Kunkleman
Maintainer-email: skunklem@uncc.edu
Requires-Python: >=3.8
Classifier: License :: OSI Approved :: MIT License
Classifier: Programming Language :: Python :: 3
Classifier: Programming Language :: Python :: 3.8
Classifier: Programming Language :: Python :: 3.9
Classifier: Programming Language :: Python :: 3.10
Classifier: Programming Language :: Python :: 3.11
Requires-Dist: biopython (>=1.78)
Requires-Dist: pandas (>=1.5)
Project-URL: Repository, https://github.com/enviro-lab/ncbi-submit
